py_eth_pairing/__init__.py
py_eth_pairing/eth_pairing_py.cpython-36m-darwin.so
py_eth_pairing-0.1.4.dist-info/LICENSE
py_eth_pairing-0.1.4.dist-info/METADATA
py_eth_pairing-0.1.4.dist-info/WHEEL
py_eth_pairing-0.1.4.dist-info/top_level.txt
py_eth_pairing-0.1.4.dist-info/RECORD
