Metadata-Version: 2.1
Name: py-eth-pairing
Version: 0.1.4
Summary: Use Ethereum precompiled pairing operations (BN128, specified in EIP196) in Python
Home-page: https://github.com/Lucieno/py_eth_pairing
Author: Lucien
Author-email: lokm13@gmail.com
License: UNKNOWN
Platform: UNKNOWN
Classifier: Programming Language :: Python :: 3
Classifier: License :: OSI Approved :: MIT License
Classifier: Operating System :: OS Independent
Requires-Python: >=3.6
